[
    {
        "AppFolder":  "app-kompas-text-sync",
        "AppPath":  "C:\\__MY_PROJECTS__\\git\\kompas3d-utility\\app-kompas-text-sync",
        "Name":  "Kompas Text Sync",
        "Program":  "C:\\__MY_PROJECTS__\\git\\kompas3d-utility\\app-kompas-text-sync\\bin\\app-kompas-text-sync.exe",
        "Arguments":  "",
        "Icon":  "C:\\__MY_PROJECTS__\\git\\kompas3d-utility\\app-kompas-text-sync\\assets\\app.ico",
        "Status":  "READY",
        "LauncherSource":  "bin/\u003capp\u003e.exe",
        "BindingFile":  "C:\\__MY_PROJECTS__\\git\\kompas3d-utility\\app-kompas-text-sync\\out\\kompas_button_binding.txt",
        "Note":  ""
    },
    {
        "AppFolder":  "app-xlsx-to-kompas-tbl",
        "AppPath":  "C:\\__MY_PROJECTS__\\git\\kompas3d-utility\\app-xlsx-to-kompas-tbl",
        "Name":  "Xlsx To Kompas Tbl",
        "Program":  "C:\\__MY_PROJECTS__\\git\\kompas3d-utility\\app-xlsx-to-kompas-tbl\\bin\\app-xlsx-to-kompas-tbl.exe",
        "Arguments":  "",
        "Icon":  "C:\\__MY_PROJECTS__\\git\\kompas3d-utility\\app-xlsx-to-kompas-tbl\\assets\\app.ico",
        "Status":  "READY",
        "LauncherSource":  "bin/\u003capp\u003e.exe",
        "BindingFile":  "C:\\__MY_PROJECTS__\\git\\kompas3d-utility\\app-xlsx-to-kompas-tbl\\out\\kompas_button_binding.txt",
        "Note":  ""
    }
]
